swarmauri_tool_githubloader/GithubLoadedTool.py
swarmauri_tool_githubloader/__init__.py
swarmauri_tool_githubloader-0.9.0.dev4.dist-info/LICENSE
swarmauri_tool_githubloader-0.9.0.dev4.dist-info/METADATA
swarmauri_tool_githubloader-0.9.0.dev4.dist-info/WHEEL
swarmauri_tool_githubloader-0.9.0.dev4.dist-info/entry_points.txt
swarmauri_tool_githubloader-0.9.0.dev4.dist-info/RECORD
